Metadata-Version: 1.1
Name: bqpjson
Version: 0.5.1
Summary: utilities for working with bqpjson data
Home-page: https://github.com/lanl-ansi/bqpjson
Author: Carleton Coffrin
Author-email: cjc@lanl.gov
License: BSD
Download-URL: https://github.com/lanl-ansi/bqpjson/archive/0.5.1.tar.gz
Platform: UNKNOWN
Classifier: Development Status :: 4 - Beta
Classifier: Intended Audience :: Developers
Classifier: License :: OSI Approved :: BSD License
Classifier: Operating System :: OS Independent
Classifier: Programming Language :: Python
Classifier: Programming Language :: Python :: 2
Classifier: Programming Language :: Python :: 2.7
Classifier: Programming Language :: Python :: 3
Classifier: Programming Language :: Python :: 3.4
Classifier: Programming Language :: Python :: 3.5
Classifier: Programming Language :: Python :: 3.6
